netstealth/__init__.py
netstealth/_version.py
netstealth/components/__init__.py
netstealth/components/browser.py
netstealth/core/__init__.py
netstealth/core/exceptions.py
netstealth/core/interfaces.py
netstealth/core/session.py
netstealth/utils/__init__.py
netstealth/utils/lazy_imports.py
netstealth-0.1.0.dist-info/METADATA
netstealth-0.1.0.dist-info/WHEEL
netstealth-0.1.0.dist-info/entry_points.txt
netstealth-0.1.0.dist-info/RECORD
