Metadata-Version: 2.4
Name: netstealth
Version: 0.1.0
Summary: Advanced stealth automation library with anti-detection browser control and proxy management
Project-URL: Homepage, https://github.com/netstealth/netstealth
Project-URL: Repository, https://github.com/netstealth/netstealth
Project-URL: Documentation, https://netstealth.readthedocs.io/
Project-URL: Issues, https://github.com/netstealth/netstealth/issues
Author-email: NetStealth Contributors <contributors@netstealth.io>
License: MIT
Keywords: anti-detection,automation,browser,fingerprint,proxy,stealth
Classifier: Development Status :: 4 - Beta
Classifier: Intended Audience :: Developers
Classifier: License :: OSI Approved :: MIT License
Classifier: Operating System :: OS Independent
Classifier: Programming Language :: Python :: 3
Classifier: Programming Language :: Python :: 3.8
Classifier: Programming Language :: Python :: 3.9
Classifier: Programming Language :: Python :: 3.10
Classifier: Programming Language :: Python :: 3.11
Classifier: Programming Language :: Python :: 3.12
Classifier: Topic :: Internet :: Proxy Servers
Classifier: Topic :: Internet :: WWW/HTTP :: Browsers
Classifier: Topic :: Security
Classifier: Topic :: Software Development :: Libraries
Requires-Python: >=3.8
Requires-Dist: pydantic>=2.0.0
Requires-Dist: requests>=2.31.0
Provides-Extra: browser
Requires-Dist: selenium>=4.15.0; extra == 'browser'
Requires-Dist: undetected-chromedriver>=3.5.0; extra == 'browser'
Provides-Extra: dev
Requires-Dist: black>=23.0.0; extra == 'dev'
Requires-Dist: build>=0.10.0; extra == 'dev'
Requires-Dist: bump2version>=1.0.1; extra == 'dev'
Requires-Dist: flake8>=6.0.0; extra == 'dev'
Requires-Dist: isort>=5.12.0; extra == 'dev'
Requires-Dist: mypy>=1.5.0; extra == 'dev'
Requires-Dist: pre-commit>=3.0.0; extra == 'dev'
Requires-Dist: pytest-asyncio>=0.21.0; extra == 'dev'
Requires-Dist: pytest-cov>=4.0.0; extra == 'dev'
Requires-Dist: pytest>=7.0.0; extra == 'dev'
Requires-Dist: twine>=4.0.0; extra == 'dev'
Provides-Extra: fingerprint
Requires-Dist: tls-client>=1.0.0; extra == 'fingerprint'
Provides-Extra: full
Requires-Dist: mitmproxy>=10.0.0; extra == 'full'
Requires-Dist: selenium>=4.15.0; extra == 'full'
Requires-Dist: tls-client>=1.0.0; extra == 'full'
Requires-Dist: undetected-chromedriver>=3.5.0; extra == 'full'
Provides-Extra: proxy
Requires-Dist: mitmproxy>=10.0.0; extra == 'proxy'
